{
  "file_name": "meta/docs/minecraft-clone/open-questions.md",
  "revisions": [
    {
      "revision_id": "f9e076a4-0a20-45c0-a80b-5179dd1351c3",
      "metadata": {
        "timestamp": "2026-03-14T00:02:21.169885",
        "type": "cache_version",
        "source": "ToolTextFileEdit",
        "size": 3055,
        "is_reverted": false,
        "git_branch_name": "",
        "agent_name": "Many",
        "description": ""
      },
      "saved_at": "2026-03-14T00:02:21.181288"
    },
    {
      "revision_id": "a8d73363-106c-4191-a8f1-a79bcff578ce",
      "metadata": {
        "timestamp": "2026-03-14T00:02:21.155847",
        "type": "cache_version",
        "source": "ToolTextFileEdit",
        "size": 0,
        "is_reverted": false,
        "git_branch_name": "",
        "agent_name": "Many",
        "description": null
      },
      "saved_at": "2026-03-14T00:02:21.163928"
    }
  ]
}