{
  "file_name": "meta/docs/minecraft-clone/performance-budget.md",
  "revision_id": "4cd330a0-5c5d-4513-8710-d59050f1970d",
  "metadata": {
    "timestamp": "2026-03-14T00:01:34.738928",
    "type": "cache_version",
    "source": "ToolTextFileEdit",
    "size": 3684,
    "is_reverted": false,
    "git_branch_name": "",
    "agent_name": "Many",
    "description": ""
  },
  "content": "---\nSECTION_ID: docs.minecraft-clone.performance-budget\nTYPE: note\n---\n\n# Performance Budget\n\n## Performance Philosophy\n\nPrimary target is **stable frametime**.\nA lower but steady frame rate is better than a high average with spikes.\n\nThe engine should always prefer:\n- bounded work\n- visible prioritization\n- graceful degradation\n- instrumentation over guesswork\n\n## Baseline Target\n\nInitial target:\n- smooth play on mid-range Windows gaming hardware typical for 2024-2026\n- stable traversal in normal terrain\n- chunk generation and upload without severe frame spikes\n\nInternal engineering target:\n- keep the main thread from accumulating unbounded world/renderer work\n- track both CPU and GPU frame time separately\n\n## Frame Budget Model\n\nTreat frame time as a fixed budget to split across:\n\n- input + game simulation\n- world streaming coordination\n- completed job integration\n- renderer submission\n- GPU execution\n- UI/debug overhead\n\nDo not let any single subsystem consume unlimited time just because work is queued.\n\n## Budget Rules\n\n### Main Thread\n- must stay predictable\n- should only integrate a capped number of completed jobs per frame\n- should cap block update propagation and chunk state transitions per frame\n\n### Worker Threads\n- can build backlog\n- must be priority-driven\n- must not flood memory with unlimited completed outputs waiting for main-thread pickup\n\n### GPU Uploads\n- cap bytes uploaded per frame\n- defer distant chunk uploads under pressure\n- prioritize chunks near player/camera\n\n## Budgeted Work Types\n\nThese operations need explicit per-frame limits:\n- chunk state transitions\n- chunk generation starts\n- completed generation commits\n- mesh build commits\n- mesh upload bytes\n- save writes kicked on gameplay path\n- block update cascades\n\n## Recommended Degradation Strategy\n\nWhen under pressure:\n\n1. reduce far-radius mesh generation priority\n2. delay non-critical transparent rebuilds\n3. lower terrain decoration generation priority\n4. keep near-player holes filled first\n5. preserve input responsiveness above visual completeness\n\nNever degrade by making controls feel laggy.\n\n## Memory Budget Rules\n\nTrack separately:\n- CPU voxel memory\n- CPU mesh staging memory\n- GPU chunk mesh memory\n- texture memory\n- upload ring memory\n- save/load buffers\n\nUse retention radius and LRU-style eviction for old chunk data.\nDo not keep both full voxel data and full mesh data for far chunks longer than necessary.\n\n## Observability Requirements\n\nExpose at runtime:\n- CPU frame time\n- GPU frame time\n- active chunk count\n- resident subchunk count\n- dirty subchunk count\n- generation queue size\n- meshing queue size\n- upload bytes this frame\n- chunk load/generate timings\n- save queue size\n\nIf it cannot be measured, it cannot be optimized safely.\n\n## Hitch Prevention\n\nAvoid:\n- synchronous disk IO on hot frame path\n- synchronous GPU waits\n- giant one-frame mesh rebuild bursts\n- full-world revalidation after local edits\n- asset decode during gameplay if preload/lazy-cache is possible\n\n## Acceptance Thresholds\n\nThe build is healthy when:\n- walking forward through unexplored terrain does not produce constant major spikes\n- placing/removing blocks only causes local, bounded rebuilds\n- opening menus/settings does not destabilize frame pacing\n- world save operations do not visibly freeze play\n\n## Optimization Order\n\nAlways optimize in this order:\n1. eliminate unbounded work\n2. reduce spikes\n3. improve locality and batching\n4. reduce average cost\n5. add complexity only if profiling proves the need\n\n## Non-Goals\n\n- chasing maximum benchmark FPS\n- overengineering GPU-driven rendering too early\n- premature micro-optimizations before instrumentation exists\n",
  "saved_at": "2026-03-14T00:01:34.738928"
}